repocleaner/__init__.py
repocleaner-1.0.1.dist-info/LICENSE
repocleaner-1.0.1.dist-info/METADATA
repocleaner-1.0.1.dist-info/WHEEL
repocleaner-1.0.1.dist-info/entry_points.txt
repocleaner-1.0.1.dist-info/top_level.txt
repocleaner-1.0.1.dist-info/RECORD
