Metadata-Version: 2.1
Name: repocleaner
Version: 1.0.1
Summary: A utility to manage GitHub repositories
Home-page: https://github.com/ELHARAKA/RepoCleaner
Author: Fahd El Haraka
Author-email: fahd@web3dev.ma
License: MIT
Classifier: Development Status :: 4 - Beta
Classifier: Intended Audience :: Developers
Classifier: Topic :: Software Development :: Version Control
Classifier: License :: OSI Approved :: MIT License
Classifier: Programming Language :: Python :: 3
Classifier: Programming Language :: Python :: 3.10
Classifier: Programming Language :: Python :: 3.6
Classifier: Programming Language :: Python :: 3.7
Classifier: Programming Language :: Python :: 3.8
Classifier: Programming Language :: Python :: 3.9
Requires-Python: >=3.10
License-File: LICENSE
Requires-Dist: pyfiglet
Requires-Dist: requests
